{
  "resource_name": "dialogflow_cx_version",
  "subcategory": "Dialogflow CX",
  "arguments": {
    "display_name": {
      "description": "The human-readable name of the version. Limit of 64 characters.",
      "required": true,
      "security_impact": null,
      "rationale": null,
      "compliant": null,
      "non-compliant": null,
      "parent": null
    },
    "description": {
      "description": "The description of the version. The maximum length is 500 characters. If exceeded, the request is rejected.",
      "required": false,
      "security_impact": null,
      "rationale": null,
      "compliant": null,
      "non-compliant": null,
      "parent": null
    },
    "parent": {
      "description": "The Flow to create an Version for. Format: projects/<Project ID>/locations/<Location ID>/agents/<Agent ID>/flows/<Flow ID>.",
      "required": false,
      "security_impact": null,
      "rationale": null,
      "compliant": null,
      "non-compliant": null,
      "parent": null
    }
  }
}