{
  "resource_name": "backup_dr_service_config",
  "subcategory": "Backup and DR Service",
  "arguments": {
    "resource_type": {
      "description": "The resource type to which the default service config will be applied.",
      "required": true,
      "security_impact": null,
      "rationale": null,
      "compliant": null,
      "non-compliant": null,
      "parent": null
    },
    "location": {
      "description": "The location in which the Service config is to be initialized.",
      "required": true,
      "security_impact": null,
      "rationale": null,
      "compliant": null,
      "non-compliant": null,
      "parent": null
    },
    "project": {
      "description": "If it is not provided, the provider project is used.",
      "required": null,
      "security_impact": null,
      "rationale": null,
      "compliant": null,
      "non-compliant": null,
      "parent": null
    }
  }
}