{
  "resource_name": "apigee_developer",
  "subcategory": "Apigee",
  "arguments": {
    "email": {
      "description": "Email address of the developer. This value is used to uniquely identify the developer in Apigee hybrid. Note that the email address has to be in lowercase only..",
      "required": true,
      "security_impact": null,
      "rationale": null,
      "compliant": null,
      "non-compliant": null,
      "parent": null
    },
    "first_name": {
      "description": "First name of the developer.",
      "required": true,
      "security_impact": null,
      "rationale": null,
      "compliant": null,
      "non-compliant": null,
      "parent": null
    },
    "last_name": {
      "description": "Last name of the developer.",
      "required": true,
      "security_impact": null,
      "rationale": null,
      "compliant": null,
      "non-compliant": null,
      "parent": null
    },
    "user_name": {
      "description": "User name of the developer. Not used by Apigee hybrid.",
      "required": true,
      "security_impact": null,
      "rationale": null,
      "compliant": null,
      "non-compliant": null,
      "parent": null
    },
    "org_id": {
      "description": "The Apigee Organization associated with the Apigee instance, in the format `organizations/{{org_name}}`.",
      "required": true,
      "security_impact": null,
      "rationale": null,
      "compliant": null,
      "non-compliant": null,
      "parent": null
    },
    "attributes": {
      "description": "Developer attributes (name/value pairs). The custom attribute limit is 18. Structure is [documented below](#nested_attributes).",
      "required": false,
      "security_impact": null,
      "rationale": null,
      "compliant": null,
      "non-compliant": null,
      "parent": null,
      "arguments": {
        "name": {
          "description": "Key of the attribute",
          "required": false,
          "security_impact": null,
          "rationale": null,
          "compliant": null,
          "non-compliant": null,
          "parent": "attributes"
        },
        "value": {
          "description": "Value of the attribute",
          "required": false,
          "security_impact": null,
          "rationale": null,
          "compliant": null,
          "non-compliant": null,
          "parent": "attributes"
        }
      }
    }
  }
}